colortextpy/__init__.py
colortextpy/_modidx.py
colortextpy/ansicolor.py
colortextpy/color.py
colortextpy/colorizer.py
colortextpy/printer.py
colortextpy-0.0.3.2.dist-info/LICENSE
colortextpy-0.0.3.2.dist-info/METADATA
colortextpy-0.0.3.2.dist-info/WHEEL
colortextpy-0.0.3.2.dist-info/entry_points.txt
colortextpy-0.0.3.2.dist-info/top_level.txt
colortextpy-0.0.3.2.dist-info/RECORD
