Metadata-Version: 2.1
Name: colortextpy
Version: 0.0.3.2
Summary: Colortextpy is a Python package for adding colors and styles to terminal output, allowing you to create more visually appealing and organized command-line applications.
Home-page: https://github.com/susuky/colortextpy
Author: ping
Author-email: hpisj322@gmail.com
License: Apache Software License 2.0
Keywords: console color terminal text formatting notebook python
Classifier: Development Status :: 4 - Beta
Classifier: Intended Audience :: Developers
Classifier: Natural Language :: English
Classifier: Programming Language :: Python :: 3.6
Classifier: Programming Language :: Python :: 3.7
Classifier: Programming Language :: Python :: 3.8
Classifier: Programming Language :: Python :: 3.9
Classifier: Programming Language :: Python :: 3.10
Classifier: License :: OSI Approved :: Apache Software License
Requires-Python: >=3.6
License-File: LICENSE
Requires-Dist: fastcore
Requires-Dist: matplotlib
Provides-Extra: dev
